{
  "OK": [
    "ok"
  ],
  "PM": [
    "pm"
  ],
  "abus": [
    "abusus"
  ],
  "agelaus": [
    "ageløs"
  ],
  "alburom": [
    "albuerom"
  ],
  "alene": [
    "aleine"
  ],
  "alimentasjon": [
    "alimentasjonsbidrag"
  ],
  "alumn": [
    "alumnus"
  ],
  "amanuens": [
    "amanuensis"
  ],
  "anatem": [
    "anatema"
  ],
  "anatemisere": [
    "anatematisere"
  ],
  "annvinn": [
    "annvint"
  ],
  "aphel": [
    "aphelium"
  ],
  "apoge": [
    "apogeum"
  ],
  "apokryf": [
    "apokryfisk"
  ],
  "arketyp": [
    "arketype"
  ],
  "askeladd": [
    "Askeladden"
  ],
  "atferd": [
    "adferd"
  ],
  "atkomst": [
    "adkomst"
  ],
  "atskille": [
    "adskille"
  ],
  "atskillelse": [
    "adskillelse"
  ],
  "atskillende": [
    "adskillende"
  ],
  "atskillig": [
    "adskillige",
    "atskillige"
  ],
  "atskilt": [
    "adskilt"
  ],
  "atspre": [
    "adspre"
  ],
  "atspredelse": [
    "adspredelse"
  ],
  "atspredt": [
    "adspredt"
  ],
  "atspredthet": [
    "adspredthet"
  ],
  "atstadig": [
    "adstadig"
  ],
  "avfjære": [
    "avfjøre"
  ],
  "avfolking": [
    "avfolkning"
  ],
  "avholdsmann": [
    "avholdskvinne"
  ],
  "avkopling": [
    "avkobling"
  ],
  "avløving": [
    "avlauving"
  ],
  "avtaker": [
    "avtager"
  ],
  "bakkels": [
    "bakkelse"
  ],
  "bakket": [
    "bakkete"
  ],
  "bandonion": [
    "bandoneon"
  ],
  "bauksitt": [
    "bauxitt"
  ],
  "bearbeidelse": [
    "bearbeiding"
  ],
  "bein": [
    "ben"
  ],
  "beinbetennelse": [
    "benbetennelse"
  ],
  "beinet": [
    "beinete"
  ],
  "beinlim": [
    "benlim"
  ],
  "beinsam": [
    "beinkesam"
  ],
  "beist": [
    "best"
  ],
  "belgtreder": [
    "belgetreder"
  ],
  "benet": [
    "benete"
  ],
  "benk": [
    "sofabenk"
  ],
  "berserkgang": [
    "berserkergang",
    "berserksgang"
  ],
  "besk": [
    "beisk"
  ],
  "bestselger": [
    "bestseller"
  ],
  "betagende": [
    "betakende"
  ],
  "bh": [
    "BH"
  ],
  "billedhogger": [
    "billedhugger",
    "bildehogger",
    "bildehugger"
  ],
  "billedhoggerarbeid": [
    "billedhuggerarbeid",
    "bildehoggerarbeid",
    "bildehuggerarbeid"
  ],
  "billedstøtte": [
    "bildestøtte"
  ],
  "bjelle": [
    "bjølle"
  ],
  "bjerkebekk": [
    "bjerkebekker"
  ],
  "blei": [
    "bleig"
  ],
  "blek": [
    "bleik"
  ],
  "blekhet": [
    "bleikhet"
  ],
  "blekne": [
    "bleikne"
  ],
  "bleknet": [
    "bleiknet"
  ],
  "bleksott": [
    "bleiksott"
  ],
  "blikkfang": [
    "blikkfanger"
  ],
  "blingset": [
    "blingsete"
  ],
  "blæret": [
    "blærete"
  ],
  "bowler": [
    "bowlerhatt"
  ],
  "brannet": [
    "brannete"
  ],
  "bred": [
    "brei"
  ],
  "bredside": [
    "breiside"
  ],
  "brems": [
    "bremse"
  ],
  "broket": [
    "brokete"
  ],
  "bru": [
    "bro"
  ],
  "brubygger": [
    "brobygger"
  ],
  "bråket": [
    "bråkete"
  ],
  "buklet": [
    "buklete"
  ],
  "buké": [
    "bouquet"
  ],
  "bulket": [
    "bulkete"
  ],
  "bumset": [
    "bumsete"
  ],
  "bursjoa": [
    "bourgeois"
  ],
  "bursjoasi": [
    "bourgeoisi"
  ],
  "bustet": [
    "bustete"
  ],
  "cellulitt": [
    "sellulitt"
  ],
  "chat": [
    "chatt"
  ],
  "crash": [
    "crashe"
  ],
  "cymbal": [
    "cymbel"
  ],
  "datasnok": [
    "datasnoker"
  ],
  "deform": [
    "deformert"
  ],
  "deiget": [
    "deigete"
  ],
  "dekan": [
    "dekanus"
  ],
  "deltakelse": [
    "deltagelse"
  ],
  "deltaker": [
    "deltager"
  ],
  "desennium": [
    "decennium"
  ],
  "dignitar": [
    "dignitær"
  ],
  "dinosaur": [
    "dinosaurus"
  ],
  "diset": [
    "disete"
  ],
  "ditto": [
    "do."
  ],
  "dobbel": [
    "dobbelt"
  ],
  "dokke": [
    "dukke"
  ],
  "dokkeaktig": [
    "dukkeaktig"
  ],
  "dottet": [
    "dottete"
  ],
  "dragspill": [
    "dragspell"
  ],
  "dras": [
    "drages"
  ],
  "drenere": [
    "drene"
  ],
  "dumpet": [
    "dumpete"
  ],
  "dustet": [
    "dustete"
  ],
  "dverglignende": [
    "dvergliknende"
  ],
  "dyrelignende": [
    "dyreliknende"
  ],
  "dødvann": [
    "dødvanne"
  ],
  "edelmod": [
    "edelmodighet"
  ],
  "edelsten": [
    "edelstein"
  ],
  "eksemsjon": [
    "eksempsjon"
  ],
  "ekstrovert": [
    "ekstrovertert"
  ],
  "elfenben": [
    "elfenbein"
  ],
  "elfenbenstårn": [
    "elfenbeinstårn"
  ],
  "elysisk": [
    "elyseisk"
  ],
  "endefram": [
    "endefrem"
  ],
  "endelse": [
    "ending"
  ],
  "endodonti": [
    "endonti"
  ],
  "enkom": [
    "einkom"
  ],
  "enquete": [
    "enkét"
  ],
  "ensyklika": [
    "encyklika"
  ],
  "epiderm": [
    "epidermis"
  ],
  "epifani": [
    "epifania"
  ],
  "espri": [
    "esprit"
  ],
  "etterligne": [
    "etterlikne"
  ],
  "etterlignende": [
    "etterliknende"
  ],
  "etterligner": [
    "etterlikner"
  ],
  "etterligning": [
    "etterlikning"
  ],
  "etterskrift": [
    "E.S."
  ],
  "fasinasjon": [
    "fascinasjon"
  ],
  "fasinere": [
    "fascinere"
  ],
  "fausket": [
    "fauskete"
  ],
  "feberframkallende": [
    "feberfremkallende"
  ],
  "feit": [
    "fet"
  ],
  "fete": [
    "feite"
  ],
  "fettet": [
    "fettete"
  ],
  "fight": [
    "fait"
  ],
  "fighte": [
    "faite"
  ],
  "fillet": [
    "fillete"
  ],
  "finish": [
    "finisj"
  ],
  "firdele": [
    "firedele"
  ],
  "fivreld": [
    "fivrelde"
  ],
  "fjantet": [
    "fjantete"
  ],
  "fjoll": [
    "fjolleri"
  ],
  "fjottet": [
    "fjottete"
  ],
  "fjære": [
    "fjøre"
  ],
  "fjøl": [
    "fjel"
  ],
  "flabbet": [
    "flabbete"
  ],
  "flammet": [
    "flammete"
  ],
  "fleipet": [
    "fleipete"
  ],
  "flesket": [
    "fleskete"
  ],
  "flintskallet": [
    "fleinskallet"
  ],
  "flisespikkeri": [
    "flisespikking"
  ],
  "floket": [
    "flokete"
  ],
  "fluks": [
    "fluksens"
  ],
  "flyveblad": [
    "flyveskrift"
  ],
  "flåset": [
    "flåsete"
  ],
  "flørtet": [
    "flørtete"
  ],
  "forbenet": [
    "forbeinet"
  ],
  "forbening": [
    "forbeining"
  ],
  "foregangsmann": [
    "foregangskvinne"
  ],
  "forenlig": [
    "forenelig"
  ],
  "foretak": [
    "foretagende",
    "foretakende"
  ],
  "forgrenet": [
    "forgreinet"
  ],
  "forgrening": [
    "forgreining"
  ],
  "forhenværende": [
    "fhv."
  ],
  "forhippen": [
    "forhippet"
  ],
  "forhistorisk": [
    "førhistorisk"
  ],
  "forhugning": [
    "forhogning"
  ],
  "forkorting": [
    "forkortelse"
  ],
  "forlengelse": [
    "forlenging"
  ],
  "forlibelse": [
    "forlibthet"
  ],
  "formgiving": [
    "formgivning"
  ],
  "formulde": [
    "formolde"
  ],
  "fornuftstridig": [
    "fornuftsstridig"
  ],
  "foroverkopling": [
    "foroverkobling"
  ],
  "forsage": [
    "forsake"
  ],
  "forsagelse": [
    "forsakelse"
  ],
  "forsvarsgren": [
    "forsvarsgrein"
  ],
  "fortvilt": [
    "fortvilet"
  ],
  "fotoapparat": [
    "fotografiapparat"
  ],
  "frakoplet": [
    "frakoblet"
  ],
  "fram": [
    "frem"
  ],
  "frambringe": [
    "frembringe"
  ],
  "frambrudd": [
    "frambrott",
    "frembrudd"
  ],
  "framby": [
    "fremby"
  ],
  "frambære": [
    "frembære"
  ],
  "framdatere": [
    "fremdatere"
  ],
  "framdrift": [
    "fremdrift"
  ],
  "framdukking": [
    "fremdukking"
  ],
  "framelske": [
    "fremelske"
  ],
  "framfall": [
    "fremfall"
  ],
  "framfaren": [
    "fremfaren"
  ],
  "framferd": [
    "fremferd"
  ],
  "framfor": [
    "fremfor"
  ],
  "framføre": [
    "fremføre"
  ],
  "framføring": [
    "fremføring",
    "fremførelse"
  ],
  "framgang": [
    "fremgang"
  ],
  "framgangsmåte": [
    "fremgangsmåte"
  ],
  "framgå": [
    "fremgå"
  ],
  "framherskende": [
    "fremherskende"
  ],
  "framheve": [
    "fremheve"
  ],
  "framheving": [
    "fremheving",
    "framhevelse",
    "fremhevelse"
  ],
  "framholde": [
    "fremholde"
  ],
  "framkalle": [
    "fremkalle"
  ],
  "framkomme": [
    "fremkomme"
  ],
  "framkommelig": [
    "fremkommelig"
  ],
  "framkomst": [
    "fremkomst"
  ],
  "framlegg": [
    "fremlegg"
  ],
  "frammane": [
    "fremmane"
  ],
  "framme": [
    "fremme"
  ],
  "frammøte": [
    "fremmøte"
  ],
  "framom": [
    "fremom"
  ],
  "framoverdrivende": [
    "fremoverdrivende"
  ],
  "framoverrettet": [
    "fremoverrettet"
  ],
  "framovervirkende": [
    "fremovervirkende"
  ],
  "frampek": [
    "frempek"
  ],
  "frampå": [
    "frempå"
  ],
  "framsi": [
    "fremsi"
  ],
  "framside": [
    "fremside"
  ],
  "framskaffe": [
    "fremskaffe"
  ],
  "framskreden": [
    "fremskreden"
  ],
  "framskritt": [
    "fremskritt"
  ],
  "framskrittsfiendtlig": [
    "fremskrittsfiendtlig"
  ],
  "framskrittsvennlig": [
    "fremskrittsvennlig"
  ],
  "framskutt": [
    "fremskutt"
  ],
  "framskynde": [
    "fremskynde"
  ],
  "framspring": [
    "fremspring"
  ],
  "framspringende": [
    "fremspringende"
  ],
  "framstille": [
    "fremstille"
  ],
  "framstilling": [
    "fremstilling"
  ],
  "framstående": [
    "fremstående"
  ],
  "framstøt": [
    "fremstøt"
  ],
  "framsyn": [
    "fremsyn"
  ],
  "framsynt": [
    "fremsynt"
  ],
  "framsynthet": [
    "fremsynthet"
  ],
  "framtid": [
    "fremtid"
  ],
  "framtidig": [
    "fremtidig"
  ],
  "framtidsbeskrivende": [
    "fremtidsbeskrivende"
  ],
  "framtidsforsker": [
    "fremtidsforsker"
  ],
  "framtil": [
    "fremtil"
  ],
  "framtoning": [
    "fremtoning"
  ],
  "framtoningspreg": [
    "fremtoningspreg"
  ],
  "framtre": [
    "fremtre"
  ],
  "framtredende": [
    "fremtredende"
  ],
  "framture": [
    "fremture"
  ],
  "framvekst": [
    "fremvekst"
  ],
  "frapperende": [
    "frappant"
  ],
  "fremtreden": [
    "framtreden"
  ],
  "frynset": [
    "frynsete"
  ],
  "fråtse": [
    "fråsse"
  ],
  "fråtser": [
    "fråsser"
  ],
  "furet": [
    "furete"
  ],
  "fyraben": [
    "fyrabend"
  ],
  "fysiatri": [
    "fysiatrikk"
  ],
  "fysn": [
    "fysne"
  ],
  "fåret": [
    "fårete"
  ],
  "game": [
    "gem"
  ],
  "gardmann": [
    "gårdmann"
  ],
  "geitet": [
    "geitete"
  ],
  "gemenslig": [
    "gemeinslig"
  ],
  "geminering": [
    "geminasjon"
  ],
  "giddeløs": [
    "giddelaus"
  ],
  "gissen": [
    "gisten"
  ],
  "gjemme": [
    "gjømme"
  ],
  "gjenbo": [
    "gjenboer",
    "gjenbuer"
  ],
  "gjennomgangsmelodi": [
    "gjennomgangstema"
  ],
  "gjennomtrekk": [
    "rask"
  ],
  "gjentakelse": [
    "gjentagelse"
  ],
  "gjentakstilfelle": [
    "gjentagelsestilfelle",
    "gjentakelsestilfelle"
  ],
  "gjenvei": [
    "gjenveg"
  ],
  "gjenvordighet": [
    "gjenvordigheter"
  ],
  "glandel": [
    "glandula"
  ],
  "glasere": [
    "glassere"
  ],
  "glass-skap": [
    "glasskap"
  ],
  "glemme": [
    "glømme"
  ],
  "gloret": [
    "glorete"
  ],
  "glugg": [
    "glugge"
  ],
  "godkjennelse": [
    "godkjenning"
  ],
  "godlidende": [
    "godlidendes"
  ],
  "godtakbar": [
    "godtagbar"
  ],
  "godtgjørelse": [
    "godtgjøring"
  ],
  "godtroen": [
    "godtroende"
  ],
  "golv": [
    "gulv"
  ],
  "gras": [
    "gress"
  ],
  "grasbakke": [
    "gressbakke"
  ],
  "graut": [
    "grøt"
  ],
  "grein": [
    "gren"
  ],
  "grimet": [
    "grimete"
  ],
  "grinet": [
    "grinete"
  ],
  "griset": [
    "grisete"
  ],
  "grissgrendt": [
    "grisgrendt"
  ],
  "gromgutt": [
    "gromjente"
  ],
  "grovhugd": [
    "grovhugget",
    "grovhogd"
  ],
  "grugget": [
    "gruggete"
  ],
  "grumset": [
    "grumsete"
  ],
  "grunngiving": [
    "grunngivning"
  ],
  "grunnmuret": [
    "grunnmura",
    "grunnmurt"
  ],
  "grøtet": [
    "grøtete"
  ],
  "guide": [
    "gaide",
    "gaid"
  ],
  "gul": [
    "gule"
  ],
  "gymnas": [
    "gymnasium"
  ],
  "gård": [
    "gard"
  ],
  "hadsj": [
    "hadj"
  ],
  "hadsji": [
    "hadji"
  ],
  "hafelle": [
    "hagfelle"
  ],
  "hagegynge": [
    "hagesofa"
  ],
  "hakket": [
    "hakkete"
  ],
  "halat": [
    "halatt"
  ],
  "halgatt": [
    "halegatt"
  ],
  "halshogge": [
    "halshugge"
  ],
  "handikap": [
    "handikapp"
  ],
  "haneben": [
    "hanebein"
  ],
  "hanglet": [
    "hanglete"
  ],
  "hardnakket": [
    "hardnakka"
  ],
  "havn": [
    "hamn"
  ],
  "heade": [
    "hedde"
  ],
  "hedenfaren": [
    "hedengangen"
  ],
  "hederskront": [
    "hederskronet"
  ],
  "heimle": [
    "hjemle"
  ],
  "hendelse": [
    "hending"
  ],
  "hengslet": [
    "hengslete"
  ],
  "hensynsløs": [
    "hensynslaus"
  ],
  "hensyntagen": [
    "hensyntaken",
    "hensyntaking"
  ],
  "het": [
    "heit"
  ],
  "hijab": [
    "hidsjab"
  ],
  "hjem": [
    "heim"
  ],
  "hjemme": [
    "heime"
  ],
  "hjemmelsmann": [
    "hjemmelskvinne",
    "hjemmelsperson",
    "heimelsmann",
    "heimelskvinne",
    "heimelsperson"
  ],
  "hjemvei": [
    "hjemveg",
    "heimveg"
  ],
  "hjernevask": [
    "hjernevasking"
  ],
  "hodegal": [
    "hodegalen"
  ],
  "hodestups": [
    "hodestupes"
  ],
  "hogg": [
    "hugg"
  ],
  "hogge": [
    "hugge"
  ],
  "hoggestabbe": [
    "huggestabbe"
  ],
  "hogging": [
    "hugging"
  ],
  "hogst": [
    "hugst"
  ],
  "holograf": [
    "holografisk"
  ],
  "homøostase": [
    "homeostase"
  ],
  "hornlignende": [
    "hornliknende"
  ],
  "hul": [
    "hol"
  ],
  "hule": [
    "hole"
  ],
  "humpet": [
    "humpete"
  ],
  "husholdere": [
    "husholderere"
  ],
  "hvil": [
    "kvil"
  ],
  "hvile": [
    "kvile"
  ],
  "hvitkløver": [
    "kvitkløver"
  ],
  "hy": [
    "hyde"
  ],
  "hyet": [
    "hyete"
  ],
  "hånd": [
    "hand"
  ],
  "håndbevegelse": [
    "handbevegelse"
  ],
  "håndbok": [
    "handbok"
  ],
  "håndfallen": [
    "handfallen"
  ],
  "håndfare": [
    "handfare"
  ],
  "håndfast": [
    "handfast"
  ],
  "håndfritt": [
    "handfritt"
  ],
  "håndfull": [
    "handfull"
  ],
  "håndgrep": [
    "handgrep"
  ],
  "håndgripelig": [
    "handgripelig"
  ],
  "håndheve": [
    "handheve"
  ],
  "håndlag": [
    "handlag"
  ],
  "håndlanger": [
    "handlanger"
  ],
  "håndskrift": [
    "handskrift"
  ],
  "håndskriftkunnskap": [
    "handskriftkunnskap"
  ],
  "håndsrekning": [
    "handsrekning"
  ],
  "håndtak": [
    "handtak"
  ],
  "håndtere": [
    "handtere"
  ],
  "håndtering": [
    "handtering"
  ],
  "håndtrykk": [
    "handtrykk"
  ],
  "håndvarm": [
    "handvarm"
  ],
  "håndvask": [
    "handvask"
  ],
  "håndvekt": [
    "handvekt"
  ],
  "håndvending": [
    "handvending"
  ],
  "håndverk": [
    "handverk"
  ],
  "håndverksmessig": [
    "handverksmessig"
  ],
  "hårdhjertet": [
    "hardhjertet"
  ],
  "hårdnakket": [
    "hardnakka",
    "hardnakket"
  ],
  "håret": [
    "hårete"
  ],
  "høyde": [
    "høgde"
  ],
  "høyskole": [
    "høgskole"
  ],
  "iakttakelse": [
    "iakttagelse"
  ],
  "iakttaker": [
    "iakttager"
  ],
  "iatri": [
    "iatrikk"
  ],
  "ilde": [
    "elde"
  ],
  "ildhug": [
    "eldhug"
  ],
  "ilsk": [
    "ilsken"
  ],
  "incentiv": [
    "insentiv"
  ],
  "innenbords": [
    "innabords"
  ],
  "innendørs": [
    "innadørs"
  ],
  "innenfor": [
    "innafor"
  ],
  "innenlands": [
    "innalands",
    "innalandsk",
    "innenlandsk"
  ],
  "innenriks": [
    "innariks",
    "innariksk",
    "innenriksk"
  ],
  "innhogg": [
    "innhugg"
  ],
  "innhul": [
    "innhol"
  ],
  "innlede": [
    "innleie"
  ],
  "innledning": [
    "innleiing"
  ],
  "innovatør": [
    "innovator"
  ],
  "innsprøyting": [
    "innsprøytning"
  ],
  "innsvingt": [
    "innsvinget"
  ],
  "input": [
    "innputt"
  ],
  "insest": [
    "incest"
  ],
  "insitament": [
    "incitament"
  ],
  "insitere": [
    "incitere"
  ],
  "insomni": [
    "insomnia"
  ],
  "intern": [
    "internt"
  ],
  "interpersonell": [
    "interpersonlig"
  ],
  "introvert": [
    "introvertert"
  ],
  "ist": [
    "idest"
  ],
  "jamlike": [
    "jevnlike"
  ],
  "jamsides": [
    "jevnsides"
  ],
  "jamstilt": [
    "jevnstilt"
  ],
  "jasket": [
    "jaskete"
  ],
  "jekkpott": [
    "jackpot"
  ],
  "jevn": [
    "jamn"
  ],
  "jevne": [
    "jamne"
  ],
  "jevnføre": [
    "jamføre"
  ],
  "jevngod": [
    "jamgod"
  ],
  "jordferd": [
    "jordeferd"
  ],
  "jordliv": [
    "jordeliv"
  ],
  "jordvidd": [
    "jordvidde"
  ],
  "junior": [
    "jr."
  ],
  "jura": [
    "jus",
    "juss"
  ],
  "jus": [
    "juice",
    "juss"
  ],
  "jålet": [
    "jålete"
  ],
  "kabelar": [
    "kabelaring"
  ],
  "kabeljau": [
    "kabeljå"
  ],
  "kakadu": [
    "kakadue"
  ],
  "kantet": [
    "kantete"
  ],
  "kas": [
    "kase"
  ],
  "kastet": [
    "kastete"
  ],
  "katt": [
    "katte"
  ],
  "kattaktig": [
    "katteaktig"
  ],
  "kavl": [
    "kavle"
  ],
  "kei": [
    "kjei"
  ],
  "keitet": [
    "keitete"
  ],
  "keivet": [
    "keivete"
  ],
  "kilde": [
    "kjelde"
  ],
  "kim": [
    "kime"
  ],
  "kiming": [
    "kimming"
  ],
  "kjelket": [
    "kjelkete"
  ],
  "klamme": [
    "klammer"
  ],
  "kleimet": [
    "kleimete"
  ],
  "klekk": [
    "kløkk"
  ],
  "klenodie": [
    "klenodium"
  ],
  "klinet": [
    "klinete"
  ],
  "klinsj": [
    "clinch"
  ],
  "klissen": [
    "klisset",
    "klissete"
  ],
  "klosset": [
    "klossete"
  ],
  "klumpet": [
    "klumpete"
  ],
  "kluntet": [
    "kluntete"
  ],
  "kløkken": [
    "kløkksam"
  ],
  "klønet": [
    "klønete"
  ],
  "knastet": [
    "knastete"
  ],
  "knockout": [
    "k.o."
  ],
  "knoklet": [
    "knoklete"
  ],
  "knortet": [
    "knortete"
  ],
  "knotet": [
    "knotete"
  ],
  "knudret": [
    "knudrete"
  ],
  "knusleri": [
    "knusling",
    "knussel"
  ],
  "knuslet": [
    "knuslete"
  ],
  "koble": [
    "kople"
  ],
  "kokke": [
    "kokkelere",
    "kokkerere"
  ],
  "kolloid": [
    "kolloidal"
  ],
  "kon": [
    "konus"
  ],
  "kondensasjon": [
    "kondensering"
  ],
  "konet": [
    "konete"
  ],
  "kongedatter": [
    "kongsdatter"
  ],
  "konsens": [
    "konsensus"
  ],
  "konserves": [
    "konserver"
  ],
  "konteiner": [
    "container"
  ],
  "kopling": [
    "kobling"
  ],
  "korg": [
    "kurv"
  ],
  "kornet": [
    "kornete"
  ],
  "korteks": [
    "cortex"
  ],
  "kortlivet": [
    "kortlevd"
  ],
  "kostgodtgjørelse": [
    "kostgodtgjøring"
  ],
  "kraftløs": [
    "kraftesløs"
  ],
  "kragekappe": [
    "kravekappe"
  ],
  "kral": [
    "kraal"
  ],
  "kranglet": [
    "kranglete"
  ],
  "kravall": [
    "kravalje"
  ],
  "kredens": [
    "kredensbord"
  ],
  "kreftfremkallende": [
    "kreftframkallende"
  ],
  "kroket": [
    "krokete"
  ],
  "krokvei": [
    "krokveier"
  ],
  "kronglet": [
    "kronglete"
  ],
  "krumspring": [
    "krumsprang"
  ],
  "kruset": [
    "krusete"
  ],
  "kruslet": [
    "kruslete"
  ],
  "krøkket": [
    "krøkkete"
  ],
  "krøllet": [
    "krøllete"
  ],
  "kullseile": [
    "kollseile",
    "kollsegle"
  ],
  "kuvet": [
    "kuvete"
  ],
  "kvapset": [
    "kvapsete"
  ],
  "kvass": [
    "hvass"
  ],
  "kvelv": [
    "kvelving"
  ],
  "kvese": [
    "hvese"
  ],
  "kvil": [
    "kvile"
  ],
  "kvin": [
    "hvin"
  ],
  "kvine": [
    "hvine"
  ],
  "kviset": [
    "kvisete"
  ],
  "kvit": [
    "hvit"
  ],
  "kåk": [
    "kåke"
  ],
  "kåket": [
    "kåkete"
  ],
  "køy": [
    "køye"
  ],
  "ladin": [
    "ladinsk",
    "ladino"
  ],
  "lage": [
    "lagje"
  ],
  "lagringsplass": [
    "lagringssted"
  ],
  "langbent": [
    "langbeint"
  ],
  "laset": [
    "lasete"
  ],
  "laten": [
    "laden"
  ],
  "lav": [
    "låg"
  ],
  "lefsetø": [
    "lefsetøyr"
  ],
  "leirvare": [
    "leirvarer"
  ],
  "lek": [
    "leik",
    "leg"
  ],
  "lekmann": [
    "legmann"
  ],
  "lekmannsskjønn": [
    "legmannsskjønn"
  ],
  "lekpredikant": [
    "legpredikant"
  ],
  "lesbarhet": [
    "leselighet"
  ],
  "lesevanske": [
    "lesevansker"
  ],
  "lett-troende": [
    "lett-truen",
    "lett-truende"
  ],
  "lettbent": [
    "lettbeint"
  ],
  "li": [
    "lide"
  ],
  "ligne": [
    "likne"
  ],
  "lignelse": [
    "liknelse"
  ],
  "lignende": [
    "liknende"
  ],
  "likblek": [
    "likbleik"
  ],
  "likefram": [
    "likefrem"
  ],
  "liknament": [
    "lignament"
  ],
  "likning": [
    "ligning"
  ],
  "liksom": [
    "likesom"
  ],
  "limbus": [
    "limbo"
  ],
  "livsledsager": [
    "livsledsagerske"
  ],
  "lortet": [
    "lortete"
  ],
  "lovmedholdig": [
    "lovmedholdelig"
  ],
  "luktende": [
    "luktendes"
  ],
  "luminescens": [
    "luminesens"
  ],
  "lunet": [
    "lunete"
  ],
  "lurvet": [
    "lurvete"
  ],
  "luset": [
    "lusete"
  ],
  "lykt": [
    "løkt"
  ],
  "lyseslokker": [
    "lyseslukker"
  ],
  "lyve": [
    "ljuge",
    "lyge"
  ],
  "løsunge": [
    "lausunge"
  ],
  "løv": [
    "lauv"
  ],
  "løvverk": [
    "lauvverk"
  ],
  "maniert": [
    "manierert"
  ],
  "manierthet": [
    "maniererthet"
  ],
  "mannheimgull": [
    "mannheimergull"
  ],
  "mannjevn": [
    "mannjamn",
    "mannjamt"
  ],
  "maquis": [
    "maki"
  ],
  "maset": [
    "masete"
  ],
  "matutin": [
    "matutinum"
  ],
  "medd": [
    "medde"
  ],
  "meget": [
    "mye"
  ],
  "mekle": [
    "megle"
  ],
  "mekler": [
    "megler"
  ],
  "mekling": [
    "megling"
  ],
  "meld": [
    "melder"
  ],
  "men": [
    "mein"
  ],
  "menneskelignende": [
    "menneskeliknende"
  ],
  "mesen": [
    "mesenat"
  ],
  "middelmåtig": [
    "middelmådig"
  ],
  "middelmåtighet": [
    "middelmådighet"
  ],
  "militærlignende": [
    "militærliknende"
  ],
  "mislighet": [
    "misligheter"
  ],
  "mokker": [
    "mokkert"
  ],
  "mold": [
    "muld"
  ],
  "molde": [
    "mulde"
  ],
  "monitoring": [
    "monitorering"
  ],
  "monosyllab": [
    "monosyllabum"
  ],
  "monstrum": [
    "monster"
  ],
  "mopset": [
    "mopsete"
  ],
  "morskap": [
    "moderskap"
  ],
  "moselignende": [
    "moseliknende"
  ],
  "mot": [
    "imot"
  ],
  "motivering": [
    "motivasjon"
  ],
  "mottakelig": [
    "mottagelig"
  ],
  "mottakelighet": [
    "mottagelighet"
  ],
  "mottakelse": [
    "mottagelse"
  ],
  "mottaker": [
    "mottager"
  ],
  "muldvarparbeid": [
    "moldvarparbeid"
  ],
  "mundering": [
    "mundur"
  ],
  "munnhuggeri": [
    "munnhoggeri"
  ],
  "munnhugges": [
    "munnhogges"
  ],
  "myglet": [
    "myglete"
  ],
  "myk": [
    "mjuk"
  ],
  "myop": [
    "myopisk"
  ],
  "myriapod": [
    "myriopod"
  ],
  "narkotika": [
    "narkotikum"
  ],
  "narsisme": [
    "narsissisme"
  ],
  "nautil": [
    "nautilus"
  ],
  "nebbet": [
    "nebbete"
  ],
  "negotium": [
    "negotie"
  ],
  "nektelse": [
    "nekting"
  ],
  "nide": [
    "nidde"
  ],
  "nikkedokke": [
    "nikkedukke"
  ],
  "nonchalanse": [
    "nonsjalanse"
  ],
  "nonchalant": [
    "nonsjalant"
  ],
  "notabene": [
    "NB"
  ],
  "nykket": [
    "nykkete"
  ],
  "nået": [
    "nuet"
  ],
  "nærtakende": [
    "nærtagende",
    "nærtaken"
  ],
  "nø": [
    "nøde"
  ],
  "ofryske": [
    "ofryskje"
  ],
  "oljet": [
    "oljete"
  ],
  "omarbeidelse": [
    "omarbeiding"
  ],
  "omfram": [
    "omframt"
  ],
  "omstridd": [
    "omstridt"
  ],
  "oppbrusing": [
    "oppbrusning"
  ],
  "opphavsmann": [
    "opphavsperson"
  ],
  "opphoping": [
    "opphopning"
  ],
  "opplesing": [
    "opplesning"
  ],
  "orgiedeltaker": [
    "orgiedeltager"
  ],
  "ortofon": [
    "ortofonisk"
  ],
  "ostrakere": [
    "ostrakisere"
  ],
  "overbygg": [
    "overbygning"
  ],
  "overfladisk": [
    "overflatisk"
  ],
  "overstryking": [
    "overstrykning"
  ],
  "paradigma": [
    "paradigme"
  ],
  "parallellkopling": [
    "parallellkobling"
  ],
  "pavet": [
    "pavete"
  ],
  "peppermø": [
    "peppermøy"
  ],
  "peremsjon": [
    "perempsjon"
  ],
  "perifer": [
    "periferisk"
  ],
  "perige": [
    "perigeum"
  ],
  "perihel": [
    "perihelium"
  ],
  "pinet": [
    "pinete"
  ],
  "pinn": [
    "pinne"
  ],
  "pirket": [
    "pirkete"
  ],
  "pistret": [
    "pistrete"
  ],
  "pjaltet": [
    "pjaltete"
  ],
  "pjasket": [
    "pjaskete"
  ],
  "pjusket": [
    "pjuskete"
  ],
  "plamas": [
    "plamasje"
  ],
  "pleura": [
    "plevra"
  ],
  "pliktskyldig": [
    "pliktskyldigst"
  ],
  "plundret": [
    "plundrete"
  ],
  "pløset": [
    "pløsete"
  ],
  "polish": [
    "polisj"
  ],
  "pompet": [
    "pompete"
  ],
  "prekavere": [
    "prekevere"
  ],
  "presumptiv": [
    "presumptivt"
  ],
  "prett": [
    "prette"
  ],
  "prikket": [
    "prikkete"
  ],
  "promemoria": [
    "PM",
    "pm"
  ],
  "prompt": [
    "prompte"
  ],
  "propedeutisk": [
    "propedevtisk"
  ],
  "prospekt": [
    "prospektus"
  ],
  "prototyp": [
    "prototype"
  ],
  "pseudonym": [
    "psevdonym"
  ],
  "pubertet": [
    "pubertetsalder"
  ],
  "purket": [
    "purkete"
  ],
  "puslet": [
    "puslete"
  ],
  "pyramidal": [
    "pyramidalsk"
  ],
  "pyset": [
    "pysete"
  ],
  "pådutte": [
    "pådytte"
  ],
  "pøbelvelde": [
    "pøbelherredømme"
  ],
  "rabb": [
    "rabbe"
  ],
  "rabdomanti": [
    "rabdomantikk"
  ],
  "race": [
    "res"
  ],
  "racer": [
    "reser"
  ],
  "rade": [
    "radde"
  ],
  "radial": [
    "radiell"
  ],
  "ragget": [
    "raggete"
  ],
  "rampet": [
    "rampete"
  ],
  "raspan": [
    "raspand"
  ],
  "razzia": [
    "rassia"
  ],
  "regenerasjon": [
    "regenerering"
  ],
  "reifikasjon": [
    "reifisering"
  ],
  "reklet": [
    "reklete"
  ],
  "rendyrke": [
    "reindyrke"
  ],
  "rengjøre": [
    "reingjøre"
  ],
  "renhold": [
    "reinhold"
  ],
  "renholder": [
    "reinholder"
  ],
  "renhårig": [
    "reinhårig"
  ],
  "renke": [
    "renker"
  ],
  "renslig": [
    "reinslig"
  ],
  "rentegodtgjørelse": [
    "rentegodtgjøring"
  ],
  "represalie": [
    "represalier"
  ],
  "residu": [
    "residuum"
  ],
  "resurs": [
    "ressurser"
  ],
  "resursperson": [
    "ressursperson"
  ],
  "retablere": [
    "reetablere"
  ],
  "rettfram": [
    "rettfrem"
  ],
  "retthaversk": [
    "retthaverisk"
  ],
  "rettlede": [
    "rettleie"
  ],
  "rettledning": [
    "rettleiing"
  ],
  "revansj": [
    "revansje"
  ],
  "riflet": [
    "riflete"
  ],
  "riklet": [
    "riklete"
  ],
  "rimtuss": [
    "rimtusse"
  ],
  "rotet": [
    "rotete"
  ],
  "rothugger": [
    "rothogger"
  ],
  "ruglet": [
    "ruglete"
  ],
  "ruklet": [
    "ruklete"
  ],
  "rusket": [
    "ruskete"
  ],
  "rutet": [
    "rutete"
  ],
  "rynket": [
    "rynkete"
  ],
  "rå": [
    "råde"
  ],
  "rølpet": [
    "rølpete"
  ],
  "røret": [
    "rørete"
  ],
  "røys": [
    "stein"
  ],
  "saliv": [
    "saliva"
  ],
  "samboer": [
    "samboerske"
  ],
  "sammenkoplingsenhet": [
    "sammenkoblingsenhet"
  ],
  "sammenlignbar": [
    "sammenliknbar"
  ],
  "sammenligne": [
    "sammenlikne"
  ],
  "sammenligning": [
    "sammenlikning"
  ],
  "sammenligningsvis": [
    "sammenlikningsvis"
  ],
  "sammenpakket": [
    "sammenpresset"
  ],
  "sammentrekning": [
    "sammentrekking"
  ],
  "sammenvoksing": [
    "sammenvoksning"
  ],
  "samråd": [
    "samråding"
  ],
  "sefard": [
    "sefardi"
  ],
  "sein": [
    "sen"
  ],
  "selvdyrking": [
    "selvdyrkelse"
  ],
  "selvgod": [
    "sjølgodsjøltilfreds"
  ],
  "selvmordsflyver": [
    "selvmordsflyger"
  ],
  "selvskreven": [
    "selvskrevet"
  ],
  "senet": [
    "senete"
  ],
  "senior": [
    "sr."
  ],
  "sfæroid": [
    "sfæroidisk"
  ],
  "sidrumpa": [
    "sidrumpet"
  ],
  "similor": [
    "semilor"
  ],
  "sipe": [
    "sippe"
  ],
  "sippet": [
    "sippete"
  ],
  "sisterne": [
    "cisterne"
  ],
  "sjanger": [
    "genre"
  ],
  "sjasket": [
    "sjaskete"
  ],
  "sjikting": [
    "sjiktning"
  ],
  "sju": [
    "syv"
  ],
  "sjusket": [
    "sjuskete"
  ],
  "sjølbestemt": [
    "selvbestemt"
  ],
  "skadesløshold": [
    "skadesløsholdelse"
  ],
  "skeiv": [
    "skjev"
  ],
  "skimlet": [
    "skimlete"
  ],
  "skinneben": [
    "skinnebein"
  ],
  "skjegget": [
    "skjeggete"
  ],
  "skjøt": [
    "skjøtt"
  ],
  "skore": [
    "skorde"
  ],
  "skranglet": [
    "skranglete"
  ],
  "skru": [
    "skrue"
  ],
  "skrukk": [
    "skrukke"
  ],
  "skrukket": [
    "skrukkete"
  ],
  "skrullet": [
    "skrullete"
  ],
  "skyet": [
    "skyete"
  ],
  "slarket": [
    "slarkete"
  ],
  "sleivet": [
    "sleivete"
  ],
  "slenget": [
    "slengete"
  ],
  "slesk": [
    "sleisk"
  ],
  "sleske": [
    "sleiske"
  ],
  "slimet": [
    "slimete"
  ],
  "slimset": [
    "slimsete"
  ],
  "sliss": [
    "slisse"
  ],
  "slokke": [
    "slukke"
  ],
  "slukne": [
    "slokne"
  ],
  "slumset": [
    "slumsete"
  ],
  "slurvet": [
    "slurvete"
  ],
  "slusket": [
    "sluskete"
  ],
  "slåpen": [
    "slåpet",
    "slåpete"
  ],
  "sløset": [
    "sløsete"
  ],
  "smøret": [
    "smørete"
  ],
  "snafset": [
    "snafsete"
  ],
  "snarvei": [
    "snarveg"
  ],
  "snauhogge": [
    "snauhugge"
  ],
  "snerpet": [
    "snerpete"
  ],
  "snirklet": [
    "snirklete"
  ],
  "snobbet": [
    "snobbete"
  ],
  "snuppet": [
    "snuppete"
  ],
  "snusket": [
    "snuskete"
  ],
  "snøvlet": [
    "snøvlete"
  ],
  "sortlaten": [
    "sortladen"
  ],
  "soset": [
    "sosete"
  ],
  "spettet": [
    "spettete"
  ],
  "spirituosa": [
    "spiritus"
  ],
  "spissbub": [
    "spissbur"
  ],
  "spraglet": [
    "spraglete"
  ],
  "spray": [
    "sprei"
  ],
  "spraye": [
    "spreie"
  ],
  "sprei": [
    "spreie"
  ],
  "spyttslikkeri": [
    "spyttslikking"
  ],
  "stavkar": [
    "stavkarl"
  ],
  "steike": [
    "steke"
  ],
  "steinet": [
    "steinete"
  ],
  "stemmegiving": [
    "stemmegivning"
  ],
  "stivbent": [
    "stivbeint"
  ],
  "storslagen": [
    "storslått"
  ],
  "strandhogg": [
    "strandhugg"
  ],
  "stri": [
    "strid",
    "stride"
  ],
  "stripet": [
    "stripete"
  ],
  "stråkfant": [
    "strokfant",
    "stråkefant"
  ],
  "strømavtaker": [
    "strømavtager"
  ],
  "stuss": [
    "bakstuss"
  ],
  "stutet": [
    "stutete"
  ],
  "støvet": [
    "støvete"
  ],
  "subbet": [
    "subbete"
  ],
  "subsumsjon": [
    "subsumpsjon"
  ],
  "suicid": [
    "suicidium"
  ],
  "sumpet": [
    "sumpete"
  ],
  "supervidere": [
    "supervisere"
  ],
  "surmaget": [
    "surmavet"
  ],
  "surven": [
    "survet",
    "survete"
  ],
  "suset": [
    "susete"
  ],
  "svampet": [
    "svampete"
  ],
  "sveltihel": [
    "sveltihjel"
  ],
  "svimet": [
    "svimete"
  ],
  "svinget": [
    "svingete"
  ],
  "svivøre": [
    "svivørde"
  ],
  "svivørslig": [
    "svivørdslig"
  ],
  "syk": [
    "sjuk"
  ],
  "symposion": [
    "symposium"
  ],
  "syvmannsstyre": [
    "sjumannsstyre"
  ],
  "syvstjernen": [
    "sjustjernen"
  ],
  "syvårig": [
    "sjuårig"
  ],
  "sædcelle": [
    "sædselle"
  ],
  "søtlaten": [
    "søtladen"
  ],
  "takkel": [
    "takkelasje"
  ],
  "tarantell": [
    "tarantella"
  ],
  "taskenspill": [
    "taskenspilleri"
  ],
  "teip": [
    "tape"
  ],
  "teknisering": [
    "teknifisering"
  ],
  "tepidarium": [
    "varmt"
  ],
  "terapeutisk": [
    "terapevtisk"
  ],
  "ternet": [
    "ternete"
  ],
  "tettvokst": [
    "tettvoksen"
  ],
  "texas": [
    "teksas"
  ],
  "tidend": [
    "tidende"
  ],
  "tilbakekopling": [
    "tilbakekobling"
  ],
  "tilgrensing": [
    "tilgrensning"
  ],
  "tilkoplet": [
    "tilkoblet"
  ],
  "tilnærmelse": [
    "tilnærmelser"
  ],
  "tilskyndelse": [
    "tilskynding"
  ],
  "tilsynsperson": [
    "tilsynskvinne",
    "tilsynsmann"
  ],
  "tilvirking": [
    "tilvirkning"
  ],
  "tilværelse": [
    "tilvær",
    "tilvære"
  ],
  "tilårskommen": [
    "tilårskommet"
  ],
  "tips": [
    "tipp"
  ],
  "tjafset": [
    "tjafsete"
  ],
  "tjenestefri": [
    "tjenestefrihet"
  ],
  "tjenstaktig": [
    "tjenesteaktig"
  ],
  "tjenstgjøre": [
    "tjenestegjøre"
  ],
  "tjenstvillig": [
    "tjenestevillig"
  ],
  "tomset": [
    "tomsete"
  ],
  "topp-punkt": [
    "toppunkt"
  ],
  "toppet": [
    "toppete"
  ],
  "topphogge": [
    "topphugge"
  ],
  "torpiditet": [
    "torpor"
  ],
  "tosket": [
    "toskete"
  ],
  "totschläger": [
    "totenschläger"
  ],
  "trangpusten": [
    "trangpustet"
  ],
  "transept": [
    "transsept"
  ],
  "translucent": [
    "translucid"
  ],
  "trau": [
    "traud"
  ],
  "trauma": [
    "traume"
  ],
  "trekk-kraft": [
    "trekkraft"
  ],
  "trenet": [
    "trenete"
  ],
  "trinitas": [
    "trinitet"
  ],
  "trollet": [
    "trollete"
  ],
  "tropp": [
    "tropper"
  ],
  "trumpet": [
    "trumpete"
  ],
  "trø": [
    "trøe"
  ],
  "trøsket": [
    "trøskete"
  ],
  "trøtt": [
    "trett"
  ],
  "trøtte": [
    "trette"
  ],
  "tube": [
    "tubus"
  ],
  "tullet": [
    "tullete"
  ],
  "tusenben": [
    "tusenbein"
  ],
  "tuslet": [
    "tuslete"
  ],
  "tusset": [
    "tussete"
  ],
  "tvefold": [
    "tvefoldig"
  ],
  "tverrhogd": [
    "tverrhugd"
  ],
  "tykk": [
    "tjukk"
  ],
  "tykksak": [
    "tjukksak"
  ],
  "tåket": [
    "tåkete"
  ],
  "tøm": [
    "tømme"
  ],
  "tøtsj": [
    "touch"
  ],
  "tøvet": [
    "tøvete"
  ],
  "tøyset": [
    "tøysete"
  ],
  "uant": [
    "uanet"
  ],
  "ubesvært": [
    "ubesværet"
  ],
  "udekt": [
    "udekket"
  ],
  "ufeilbar": [
    "ufeilbarlig"
  ],
  "ufeilbarhet": [
    "ufeilbarlighet"
  ],
  "uforlignelig": [
    "uforliknelig"
  ],
  "uframkommelig": [
    "ufremkommelig"
  ],
  "ufriske": [
    "ufriskje"
  ],
  "uhel": [
    "uheil"
  ],
  "uhåndterlig": [
    "uhandterlig"
  ],
  "ukalt": [
    "ukallet"
  ],
  "ulaglig": [
    "ulagelig"
  ],
  "underskudd": [
    "underskott"
  ],
  "ungmø": [
    "ungmøy"
  ],
  "univers": [
    "universet"
  ],
  "unntak": [
    "unntagelse",
    "unntakelse"
  ],
  "unntaksmenneske": [
    "unntagelsesmenneske",
    "unntakelsesmenneske"
  ],
  "uren": [
    "urein"
  ],
  "urenslig": [
    "ureinslig"
  ],
  "utblåsing": [
    "utblåsning"
  ],
  "utdannelse": [
    "utdanning"
  ],
  "utendørs": [
    "utadørs"
  ],
  "utenfor": [
    "utafor"
  ],
  "utenforstående": [
    "utaforstående"
  ],
  "utenskjærs": [
    "utaskjærs"
  ],
  "utkik": [
    "utkikk"
  ],
  "utligne": [
    "utlikne"
  ],
  "utrere": [
    "outrere"
  ],
  "utrøttelig": [
    "utrettelig"
  ],
  "utsider": [
    "outsider"
  ],
  "uutslokkelig": [
    "uutslukkelig"
  ],
  "vakuol": [
    "vakuole"
  ],
  "valbjørk": [
    "valbjerk"
  ],
  "valpet": [
    "valpete"
  ],
  "vankundighet": [
    "vankunne"
  ],
  "vannfall": [
    "vassfall"
  ],
  "vannløs": [
    "vasslaus"
  ],
  "vannsyk": [
    "vass-sjuk"
  ],
  "vanvøre": [
    "vanvørde"
  ],
  "varamann": [
    "varakvinne"
  ],
  "varselrop": [
    "varselsrop"
  ],
  "vaset": [
    "vasete"
  ],
  "vaskekte": [
    "vaskeekte"
  ],
  "vei": [
    "veg"
  ],
  "velformet": [
    "vel"
  ],
  "vellykt": [
    "vellykket"
  ],
  "veltruffen": [
    "veltruffet"
  ],
  "vidvank": [
    "vidvanke"
  ],
  "vimset": [
    "vimsete"
  ],
  "vinglet": [
    "vinglete"
  ],
  "viskos": [
    "viskøs"
  ],
  "vitenskapsmann": [
    "vitenskapskvinne"
  ],
  "vitsmaker": [
    "vitsemaker"
  ],
  "vogge": [
    "vugge"
  ],
  "vommet": [
    "vommete"
  ],
  "vorr": [
    "vor"
  ],
  "vortelignende": [
    "vorteliknende"
  ],
  "vovet": [
    "våget"
  ],
  "vrier": [
    "vrider"
  ],
  "vå": [
    "våde"
  ],
  "våghals": [
    "vågehals"
  ],
  "vøre": [
    "vørde"
  ],
  "vørnad": [
    "vørdnad"
  ],
  "yndighet": [
    "yndigheter"
  ],
  "årveg": [
    "årvei"
  ],
  "ærendssvenn": [
    "ærendssvein"
  ],
  "ættegransking": [
    "ættegranskning"
  ],
  "ødematisk": [
    "ødematøs"
  ],
  "ørekyt": [
    "ørekyte"
  ],
  "øretuteri": [
    "øretuting"
  ],
  "øyboer": [
    "øybuer"
  ],
  "øyenbedrag": [
    "øyebedrag"
  ],
  "øyentjener": [
    "øyenskalk"
  ],
  "øyesten": [
    "øyenstein"
  ],
  "øyestikker": [
    "øyenstikker"
  ]
}
